byted_overpass_life_trade_movie_search/__init__.py
byted_overpass_life_trade_movie_search-0.0.1.dist-info/METADATA
byted_overpass_life_trade_movie_search-0.0.1.dist-info/WHEEL
byted_overpass_life_trade_movie_search-0.0.1.dist-info/top_level.txt
byted_overpass_life_trade_movie_search-0.0.1.dist-info/RECORD
